pytest_asgi_server/__init__.py
pytest_asgi_server/clients.py
pytest_asgi_server/errors.py
pytest_asgi_server/plugin.py
pytest_asgi_server/servers.py
pytest_asgi_server/utils.py
pytest_asgi_server-0.2.4.dist-info/LICENSE
pytest_asgi_server-0.2.4.dist-info/WHEEL
pytest_asgi_server-0.2.4.dist-info/METADATA
pytest_asgi_server-0.2.4.dist-info/RECORD
