Metadata-Version: 2.1
Name: pytest-asgi-server
Version: 0.2.4
Summary: Convenient ASGI client/server fixtures for Pytest
Home-page: https://github.com/garytyler/pytest-asgi-server
License: MIT
Author: Gary Tyler
Author-email: mail@garytyler.com
Requires-Python: >=3.8,<4.0
Classifier: Environment :: Plugins
Classifier: Environment :: Web Environment
Classifier: Framework :: AsyncIO
Classifier: Framework :: Pytest
Classifier: Framework :: tox
Classifier: License :: OSI Approved :: MIT License
Classifier: Programming Language :: Python :: 3
Classifier: Programming Language :: Python :: 3.8
Classifier: Programming Language :: Python :: 3.9
Classifier: Topic :: Internet :: WWW/HTTP :: HTTP Servers
Classifier: Topic :: Software Development :: Testing
Classifier: Topic :: System :: Networking
Requires-Dist: asgi-lifespan (>=1.0.0)
Requires-Dist: httpx (>=0.12.1)
Requires-Dist: importlib_metadata (>=1.6.0,<2.0.0); python_version >= "3.8"
Requires-Dist: pytest (>=5.4.1)
Requires-Dist: pytest-asyncio (>=0.10.0)
Requires-Dist: pytest-xprocess (>=0.13.1)
Requires-Dist: uvicorn (>=0.11.3)
Requires-Dist: websockets (>=8,<9); python_version >= "3.8"
Project-URL: Repository, https://github.com/garytyler/pytest-asgi-server
